openmldb/__init__.py
openmldb/dbapi/__init__.py
openmldb/dbapi/dbapi.py
openmldb/native/__init__.py
openmldb/native/_sql_router_sdk.so
openmldb/native/sql_router_sdk.py
openmldb/sdk/__init__.py
openmldb/sdk/sdk.py
openmldb/sql_magic/__init__.py
openmldb/sql_magic/sql_magic.py
openmldb/sqlalchemy_openmldb/__init__.py
openmldb/sqlalchemy_openmldb/openmldb_dialect.py
openmldb/sqlalchemy_openmldb/requirements.py
openmldb-0.9.2.dist-info/METADATA
openmldb-0.9.2.dist-info/WHEEL
openmldb-0.9.2.dist-info/entry_points.txt
openmldb-0.9.2.dist-info/top_level.txt
openmldb-0.9.2.dist-info/RECORD
