Metadata-Version: 2.1
Name: openmldb
Version: 0.9.2
Summary: OpenMLDB Python SDK
Home-page: https://github.com/4paradigm/OpenMLDB
Author: OpenMLDB Team
Author-email: 
License: copyright 4paradigm.com
Classifier: Programming Language :: Python :: 3
Requires-Dist: importlib-metadata <5.0
Requires-Dist: sqlalchemy <=2.0.27
Requires-Dist: IPython <=7.30.1
Requires-Dist: prettytable <=3.1.0
Provides-Extra: test
Requires-Dist: pytest ; extra == 'test'
Requires-Dist: tox ; extra == 'test'
